b64tensors/__init__.py
b64tensors-0.2.0.dist-info/licenses/LICENSE
b64tensors-0.2.0.dist-info/METADATA
b64tensors-0.2.0.dist-info/WHEEL
b64tensors-0.2.0.dist-info/top_level.txt
b64tensors-0.2.0.dist-info/RECORD
