Metadata-Version: 2.4
Name: b64tensors
Version: 0.2.0
Summary: Base64 tensor encoding and decoding for PyTorch tensors
Author: b64tensors contributors
License:                                  Apache License
Project-URL: Homepage, https://github.com/44670/b64tensors
Project-URL: Repository, https://github.com/44670/b64tensors
Project-URL: Issues, https://github.com/44670/b64tensors/issues
Classifier: Development Status :: 3 - Alpha
Classifier: Intended Audience :: Developers
Classifier: License :: OSI Approved :: Apache Software License
Classifier: Programming Language :: Python :: 3
Classifier: Programming Language :: Python :: 3.8
Classifier: Programming Language :: Python :: 3.9
Classifier: Programming Language :: Python :: 3.10
Classifier: Programming Language :: Python :: 3.11
Classifier: Programming Language :: Python :: 3.12
Classifier: Programming Language :: Python :: 3.13
Classifier: Topic :: Scientific/Engineering :: Artificial Intelligence
Classifier: Topic :: Software Development :: Libraries :: Python Modules
Requires-Python: >=3.8
License-File: LICENSE
Requires-Dist: safetensors>=0.5.3
Dynamic: license-file
